ptvulnsearcher/__init__.py
ptvulnsearcher/_version.py
ptvulnsearcher/ptvulnsearcher.py
ptvulnsearcher-0.0.2.dist-info/LICENSE
ptvulnsearcher-0.0.2.dist-info/METADATA
ptvulnsearcher-0.0.2.dist-info/WHEEL
ptvulnsearcher-0.0.2.dist-info/entry_points.txt
ptvulnsearcher-0.0.2.dist-info/top_level.txt
ptvulnsearcher-0.0.2.dist-info/RECORD
