Metadata-Version: 2.1
Name: ptvulnsearcher
Version: 0.0.2
Summary: Tool for searching CVE (Common Vulnerabilities and Exposures)
Home-page: https://www.penterep.com/
Author: Penterep
Author-email: info@penterep.com
License: GPLv3+
Classifier: Programming Language :: Python :: 3
Classifier: Programming Language :: Python :: Implementation :: CPython
Classifier: Environment :: Console
Classifier: Topic :: Security
Classifier: License :: OSI Approved :: GNU General Public License v3 or later (GPLv3+)
Requires-Python: >=3.6
License-File: LICENSE
Requires-Dist: ptlibs (<2,>=1)
Requires-Dist: requests
